instrumentpy/__init__.py
instrumentpy/common/common_device_interface.py
instrumentpy/common/connection_method.py
instrumentpy/common/serial_device.py
instrumentpy/common/tcpip_device.py
instrumentpy/common/unsupported_communication_method.py
instrumentpy/platform/__init__.py
instrumentpy/platform/next/__init__.py
instrumentpy/platform/next/ts3.py
instrumentpy/psu/__init__.py
instrumentpy/psu/aimtti/__init__.py
instrumentpy/psu/aimtti/mx100tp.py
instrumentpy-1.0.3.dist-info/METADATA
instrumentpy-1.0.3.dist-info/WHEEL
instrumentpy-1.0.3.dist-info/licenses/LICENSE
instrumentpy-1.0.3.dist-info/RECORD
