Metadata-Version: 2.1
Name: instrumentpy
Version: 1.0.3
Summary: A library for controlling various instruments through Python.
Project-URL: Homepage, https://github.com/jonasclaes/instrumentpy
Project-URL: Bug Tracker, https://github.com/jonasclaes/instrumentpy/issues
Author-email: Jonas Claes <jonas@jonasclaes.be>
License:                                  Apache License
Classifier: License :: OSI Approved :: MIT License
Classifier: Operating System :: OS Independent
Classifier: Programming Language :: Python :: 3
Requires-Python: >=3.7
Requires-Dist: crc
Requires-Dist: pyserial
